arg_parser/__init__.py
arg_parser/__main__.py
arg_parser/arg_parser.py
arg_parser/args.py
arg_parser/parser.py
arg_parser-1.0.5.dist-info/LICENSE
arg_parser-1.0.5.dist-info/METADATA
arg_parser-1.0.5.dist-info/WHEEL
arg_parser-1.0.5.dist-info/top_level.txt
arg_parser-1.0.5.dist-info/RECORD
