Metadata-Version: 2.1
Name: arg-parser
Version: 1.0.5
Summary: A tool for parsing arguments from the command line to a dictionary and for executing predefined on_command functions.
Home-page: https://github.com/NightKylo/Python-Arg-Parser
Author: Marius K. / cracksii
License: Apache
Platform: UNKNOWN
Classifier: License :: OSI Approved :: Apache Software License
Classifier: Programming Language :: Python :: 3
Classifier: Programming Language :: Python :: 3.9
